godirect/__init__.py
godirect/backend.py
godirect/backend_ble.py
godirect/backend_bleak.py
godirect/backend_usb.py
godirect/bleak_scan.py
godirect/device.py
godirect/device_ble.py
godirect/device_bleak.py
godirect/device_usb.py
godirect/sensor.py
godirect-1.1.3.dist-info/LICENSE
godirect-1.1.3.dist-info/METADATA
godirect-1.1.3.dist-info/WHEEL
godirect-1.1.3.dist-info/top_level.txt
godirect-1.1.3.dist-info/RECORD
