Metadata-Version: 2.1
Name: godirect
Version: 1.1.3
Summary: Library to interface with GoDirect devices via USB and BLE
Home-page: https://github.com/vernierst/godirect-py
Author: Vernier Software and Technology
Author-email: info@vernier.com
License: UNKNOWN
Platform: UNKNOWN
Classifier: Programming Language :: Python :: 3
Classifier: License :: OSI Approved :: GNU General Public License v3 (GPLv3)
Classifier: Operating System :: OS Independent
Requires-Dist: hidapi
Requires-Dist: bleak
